AUTHORS
COPYING
MANIFEST.in
README
README.md
setup.cfg
setup.py
doc/Makefile
doc/appendix.rst
doc/dcpwr.rst
doc/examples.rst
doc/fgen.rst
doc/index.rst
doc/intro.rst
doc/ivi.rst
doc/make.bat
doc/newdriver.rst
doc/scope.rst
ivi/__init__.py
ivi/counter.py
ivi/dcpwr.py
ivi/dmm.py
ivi/fgen.py
ivi/ivi.py
ivi/pwrmeter.py
ivi/rfsiggen.py
ivi/scope.py
ivi/specan.py
ivi/swtch.py
ivi/version.py
ivi/agilent/__init__.py
ivi/agilent/agilent2000A.py
ivi/agilent/agilent3000A.py
ivi/agilent/agilent34401A.py
ivi/agilent/agilent34410A.py
ivi/agilent/agilent34411A.py
ivi/agilent/agilent4000A.py
ivi/agilent/agilent436A.py
ivi/agilent/agilent437B.py
ivi/agilent/agilent6000.py
ivi/agilent/agilent6030A.py
ivi/agilent/agilent6031A.py
ivi/agilent/agilent6032A.py
ivi/agilent/agilent6033A.py
ivi/agilent/agilent6035A.py
ivi/agilent/agilent6038A.py
ivi/agilent/agilent603xA.py
ivi/agilent/agilent7000.py
ivi/agilent/agilent7000A.py
ivi/agilent/agilent7000B.py
ivi/agilent/agilent8156A.py
ivi/agilent/agilent8340A.py
ivi/agilent/agilent8340B.py
ivi/agilent/agilent8341A.py
ivi/agilent/agilent8341B.py
ivi/agilent/agilent85644A.py
ivi/agilent/agilent85645A.py
ivi/agilent/agilent8590A.py
ivi/agilent/agilent8590B.py
ivi/agilent/agilent8590E.py
ivi/agilent/agilent8590L.py
ivi/agilent/agilent8591A.py
ivi/agilent/agilent8591C.py
ivi/agilent/agilent8591E.py
ivi/agilent/agilent8591EM.py
ivi/agilent/agilent8592A.py
ivi/agilent/agilent8592B.py
ivi/agilent/agilent8592L.py
ivi/agilent/agilent8593A.py
ivi/agilent/agilent8593E.py
ivi/agilent/agilent8593EM.py
ivi/agilent/agilent8594A.py
ivi/agilent/agilent8594E.py
ivi/agilent/agilent8594EM.py
ivi/agilent/agilent8594L.py
ivi/agilent/agilent8594Q.py
ivi/agilent/agilent8595A.py
ivi/agilent/agilent8595E.py
ivi/agilent/agilent8595EM.py
ivi/agilent/agilent8596E.py
ivi/agilent/agilent8596EM.py
ivi/agilent/agilent86140B.py
ivi/agilent/agilent86141B.py
ivi/agilent/agilent86142B.py
ivi/agilent/agilent86144B.py
ivi/agilent/agilent86145B.py
ivi/agilent/agilent86146B.py
python_ivi.egg-info/PKG-INFO
python_ivi.egg-info/SOURCES.txt
python_ivi.egg-info/dependency_links.txt
python_ivi.egg-info/requires.txt
python_ivi.egg-info/top_level.txt